odoo9_addon_l10n_es_partner-9.0.1.0.1-py2.7-nspkg.pth
odoo_addons/l10n_es_partner/__openerp__.py
odoo_addons/l10n_es_partner/__init__.py
odoo_addons/l10n_es_partner/README.rst
odoo_addons/l10n_es_partner/migrations/9.0.1.0.0/post-migration.py
odoo_addons/l10n_es_partner/gen_src/bics.xls
odoo_addons/l10n_es_partner/gen_src/gen_data_banks.py
odoo_addons/l10n_es_partner/gen_src/__init__.py
odoo_addons/l10n_es_partner/gen_src/README.rst
odoo_addons/l10n_es_partner/models/res_partner.py
odoo_addons/l10n_es_partner/models/account_journal.py
odoo_addons/l10n_es_partner/models/res_bank.py
odoo_addons/l10n_es_partner/models/res_partner_bank.py
odoo_addons/l10n_es_partner/models/__init__.py
odoo_addons/l10n_es_partner/i18n/ru.po
odoo_addons/l10n_es_partner/i18n/pt.po
odoo_addons/l10n_es_partner/i18n/es.po
odoo_addons/l10n_es_partner/i18n/tr.po
odoo_addons/l10n_es_partner/i18n/hr.po
odoo_addons/l10n_es_partner/i18n/bg.po
odoo_addons/l10n_es_partner/i18n/gl.po
odoo_addons/l10n_es_partner/i18n/ca.po
odoo_addons/l10n_es_partner/i18n/es_CR.po
odoo_addons/l10n_es_partner/i18n/es_CO.po
odoo_addons/l10n_es_partner/i18n/sl.po
odoo_addons/l10n_es_partner/i18n/cs.po
odoo_addons/l10n_es_partner/i18n/eu.po
odoo_addons/l10n_es_partner/i18n/nl.po
odoo_addons/l10n_es_partner/i18n/vi.po
odoo_addons/l10n_es_partner/i18n/fr.po
odoo_addons/l10n_es_partner/i18n/pl.po
odoo_addons/l10n_es_partner/i18n/pt_BR.po
odoo_addons/l10n_es_partner/i18n/sv.po
odoo_addons/l10n_es_partner/wizard/l10n_es_partner_wizard.xml
odoo_addons/l10n_es_partner/wizard/data_banks.xml
odoo_addons/l10n_es_partner/wizard/__init__.py
odoo_addons/l10n_es_partner/wizard/l10n_es_partner_wizard.py
odoo_addons/l10n_es_partner/views/res_partner_view.xml
odoo_addons/l10n_es_partner/views/account_journal_view.xml
odoo_addons/l10n_es_partner/views/res_bank_view.xml
odoo_addons/l10n_es_partner/views/res_partner_bank_view.xml
odoo_addons/l10n_es_partner/data/l10n_es_partner_data.xml
odoo9_addon_l10n_es_partner-9.0.1.0.1.dist-info/top_level.txt
odoo9_addon_l10n_es_partner-9.0.1.0.1.dist-info/WHEEL
odoo9_addon_l10n_es_partner-9.0.1.0.1.dist-info/RECORD
odoo9_addon_l10n_es_partner-9.0.1.0.1.dist-info/metadata.json
odoo9_addon_l10n_es_partner-9.0.1.0.1.dist-info/DESCRIPTION.rst
odoo9_addon_l10n_es_partner-9.0.1.0.1.dist-info/METADATA
odoo9_addon_l10n_es_partner-9.0.1.0.1.dist-info/namespace_packages.txt
